zwnlp/__init__.py
zwnlp/__version__.py
zwnlp/ner.py
zwnlp/stats.py
zwnlp/utils.py
zwnlp-0.0.16.dist-info/LICENSE
zwnlp-0.0.16.dist-info/METADATA
zwnlp-0.0.16.dist-info/WHEEL
zwnlp-0.0.16.dist-info/top_level.txt
zwnlp-0.0.16.dist-info/RECORD
