Metadata-Version: 2.1
Name: zwnlp
Version: 0.0.16
Summary: Personal NLP task utils.
Home-page: https://github.com/njzhaowei/zwnlp
Author: Zhao Wei
Author-email: yewberry@163.com
License: Apache 2.0
Platform: all
Classifier: Programming Language :: Python :: 3
Classifier: License :: OSI Approved :: Apache Software License
Classifier: Operating System :: OS Independent
Requires-Python: >=3.6
License-File: LICENSE
Requires-Dist: protobuf (==3.6.1)
Requires-Dist: zwdb
Requires-Dist: zwutils
Requires-Dist: pyhanlp
Requires-Dist: stanza
Requires-Dist: langid
Requires-Dist: PyMuPDF
Requires-Dist: xlwt
